{
  "@id": "71b4b2f3376f3e5ca9f2642335811aead89dc30f0f327727695227599cd3a503",
  "@special~": "JSON notoriously doesn't have comments, so pay attention.",
  "@name": "fabric",
  "@link": "fabric",
  "@type": "Vector",
  "@sort": "strict",
  "@author": "martindale",
  "@comment": "The Vector meta-type is the 'bootstrap' function of the Fabric State Machine (the 'FSM'~ :D).  With a valid Vector `v_1` and a shared secret `s'`, we can compute any finite state `v_n`.",
  "@genesis": "dev#defines-index",
  "@contract~?": "@genesis/id",
  "@data": {
    "peers": [
      "127.0.0.1",
      "localhost",
      "maki.io",
      "fabric.fm",
      "converse.fm",
      "soundtrack.io",
      "ericmartindale.com",
      "roleplaygateway.com",
      "next.maki.io",
      "next.fabric.fm",
      "next.ericmartindale.com",
      "next.roleplaygateway.com",
      "verse.im",
      "next.verse.im"
    ],
    "services": {
      "http": true,
      "tcp": true
    },
    "resources": {
      "@comment": "Loosely describes a genesis `_lookup`.",
      "Index~": "/?id=0#bootstrap"
    },
    "expectations": [
      "keys", "assets",
      "blocks", "transactions",
      "names", "identities",
      "components", "resources", "services", "plugins",
      "peers", "events",
      "sessions"
    ],
    "plugins": [
      "free"
    ]
  },
  "root": {
    "id": "739c0f6067efff96f6f8f66accc1cf85c9b6cc63e8e0a16f4dead4e471a48b79"
  }
}
